Metadata-Version: 2.1
Name: twexit
Version: 6.43.0b1
Summary: Telnyx Twexit API client
Home-page: https://github.com/team-telnyx/twexit-python/
Author: Telnyx
Author-email: support@telnyx.com
License: UNKNOWN
Keywords: telnyx,twexit,texml,twilio,twiml
Platform: UNKNOWN
Classifier: Development Status :: 5 - Production/Stable
Classifier: Intended Audience :: Developers
Classifier: License :: OSI Approved :: MIT License
Classifier: Operating System :: OS Independent
Classifier: Programming Language :: Python
Classifier: Programming Language :: Python :: 2.7
Classifier: Programming Language :: Python :: 3.4
Classifier: Programming Language :: Python :: 3.5
Classifier: Programming Language :: Python :: 3.6
Classifier: Programming Language :: Python :: 3.7
Classifier: Programming Language :: Python :: 3.8
Classifier: Programming Language :: Python :: Implementation :: CPython
Classifier: Topic :: Software Development :: Libraries :: Python Modules
Classifier: Topic :: Communications :: Telephony
Requires-Dist: six
Requires-Dist: pytz
Requires-Dist: PyJWT (>=1.4.2)
Requires-Dist: requests[security] (>=2.0.0) ; python_version<"3.0"
Requires-Dist: requests (>=2.0.0) ; python_version>="3.0"
Provides-Extra: request_validator
Requires-Dist: PyNaCl ; extra == 'request_validator'
